ryoken/__init__.py
ryoken/b64.py
ryoken/collections.py
ryoken/exceptions.py
ryoken/json.py
ryoken/regexes.py
ryoken/tokenizer.py
ryoken-0.0.5.dist-info/DESCRIPTION.rst
ryoken-0.0.5.dist-info/METADATA
ryoken-0.0.5.dist-info/RECORD
ryoken-0.0.5.dist-info/WHEEL
ryoken-0.0.5.dist-info/metadata.json
ryoken-0.0.5.dist-info/top_level.txt
